{
  "FRANCE": {
    "CustomerJobCode": "TO259",
    "AgencyCode": null
  },
  "000873": {
    "CustomerJobCode": "TO259",
    "AgencyCode": "349"
  },
  "000869": {
    "CustomerJobCode": "TO259",
    "AgencyCode": "349"
  },
  "000872": {
    "CustomerJobCode": "TO259",
    "AgencyCode": "349"
  },
  "000880": {
    "CustomerJobCode": "TO259",
    "AgencyCode": "349"
  },
  "000879": {
    "CustomerJobCode": "TO259",
    "AgencyCode": "349"
  },
  "000878": {
    "CustomerJobCode": "TO259",
    "AgencyCode": "349"
  },
  "000883": {
    "CustomerJobCode": "TO259",
    "AgencyCode": "349"
  },
  "000881": {
    "CustomerJobCode": "TO259",
    "AgencyCode": "349"
  },
  "000886": {
    "CustomerJobCode": "TO259",
    "AgencyCode": "349"
  },
  "000885": {
    "CustomerJobCode": "TO259",
    "AgencyCode": "349"
  },
  "000365": {
    "CustomerJobCode": "TO259",
    "AgencyCode": "VEN"
  },
  "000893": {
    "CustomerJobCode": "TO259",
    "AgencyCode": "349"
  },
  "000895": {
    "CustomerJobCode": "TO259",
    "AgencyCode": "349"
  },
  "000891": {
    "CustomerJobCode": "TO259",
    "AgencyCode": "349"
  },
  "000897": {
    "CustomerJobCode": "TO259",
    "AgencyCode": "349"
  },
  "000069": {
    "CustomerJobCode": "TE212",
    "AgencyCode": "750"
  },
  "000907": {
    "CustomerJobCode": "TO259",
    "AgencyCode": "349"
  },
  "000566": {
    "CustomerJobCode": "TO259",
    "AgencyCode": "ARF"
  },
  "000875": {
    "CustomerJobCode": "TO258",
    "AgencyCode": "TOG"
  },
  "000567": {
    "CustomerJobCode": "TE014",
    "AgencyCode": "ARF"
  },
  "000569": {
    "CustomerJobCode": "TO259",
    "AgencyCode": "ARF"
  }
}